nerd/__init__.py
nerd/__main__.py
nerd/ner.py
ner_d-0.4.0.dist-info/COPYING
ner_d-0.4.0.dist-info/LICENSE
ner_d-0.4.0.dist-info/METADATA
ner_d-0.4.0.dist-info/NOTICE
ner_d-0.4.0.dist-info/WHEEL
ner_d-0.4.0.dist-info/top_level.txt
ner_d-0.4.0.dist-info/RECORD
