Metadata-Version: 2.1
Name: ner-d
Version: 0.4.0
Summary: Python module for Named Entity Recognition (NER).
Home-page: https://github.com/verifid/ner-d
Author: Abdullah Selek
Author-email: abdullahselek@gmail.com
Maintainer: Abdullah Selek
Maintainer-email: abdullahselek@gmail.com
License: MIT License
Download-URL: https://pypi.org/project/ner-d/
Keywords: ner,named-entity recognition,recognition,natural language processing
Platform: Any
Classifier: Intended Audience :: Developers
Classifier: License :: OSI Approved :: MIT License
Classifier: Operating System :: OS Independent
Classifier: Topic :: Software Development :: Libraries :: Python Modules
Classifier: Programming Language :: Python
Classifier: Programming Language :: Python :: 3.6
Classifier: Programming Language :: Python :: 3.7
Classifier: Programming Language :: Python :: 3.8
Requires-Dist: spacy (==2.2.2)
